LICENSE
MANIFEST.in
README.md
VERSION
requirements.txt
setup.py
clams/__init__.py
clams/app/__init__.py
clams/appmetadata/__init__.py
clams/develop/__init__.py
clams/develop/templates/app/.dockerignore.template
clams/develop/templates/app/.gitignore.template
clams/develop/templates/app/Containerfile.template
clams/develop/templates/app/LICENSE.template
clams/develop/templates/app/README.md.template
clams/develop/templates/app/app.py.template
clams/develop/templates/app/cli.py.template
clams/develop/templates/app/metadata.py.template
clams/develop/templates/app/requirements.txt.template
clams/develop/templates/gha/for-clams-team.md.template
clams/develop/templates/gha/workflows/issue-apps-project.yml.template
clams/develop/templates/gha/workflows/issue-assign.yml.template
clams/develop/templates/gha/workflows/issue-close.yml.template
clams/develop/templates/gha/workflows/publish.yml.template
clams/restify/__init__.py
clams/serve/__init__.py
clams/ver/__init__.py
clams_python.egg-info/PKG-INFO
clams_python.egg-info/SOURCES.txt
clams_python.egg-info/dependency_links.txt
clams_python.egg-info/entry_points.txt
clams_python.egg-info/requires.txt
clams_python.egg-info/top_level.txt
tests/test_clamsapp.py