Metadata-Version: 2.4
Name: clams-python
Version: 1.3.2
Summary: A collection of APIs to develop CLAMS app for python
Home-page: https://clams.ai
Author: Brandeis Lab for Linguistics and Computation
Author-email: admin@clams.ai
License: Apache-2.0
Classifier: Development Status :: 5 - Production/Stable
Classifier: Framework :: Flask
Classifier: Framework :: Pytest
Classifier: Intended Audience :: Developers
Classifier: Programming Language :: Python :: 3 :: Only
Requires-Python: >=3.10
License-File: LICENSE
Requires-Dist: mmif-python==1.1.1
Requires-Dist: Flask>=2
Requires-Dist: Flask-RESTful>=0.3.9
Requires-Dist: gunicorn>=20
Requires-Dist: lapps>=0.0.2
Requires-Dist: pydantic>=2
Requires-Dist: jsonschema>=3
Dynamic: author
Dynamic: author-email
Dynamic: classifier
Dynamic: description
Dynamic: description-content-type
Dynamic: home-page
Dynamic: license
Dynamic: license-file
Dynamic: requires-dist
Dynamic: requires-python
Dynamic: summary
